llama_index/llms/huggingface/__init__.py
llama_index/llms/huggingface/base.py
flying_delta_llms_huggingface-0.1.0.dist-info/METADATA
flying_delta_llms_huggingface-0.1.0.dist-info/WHEEL
flying_delta_llms_huggingface-0.1.0.dist-info/RECORD
